robot_description_builder-0.0.3.dist-info/METADATA
robot_description_builder-0.0.3.dist-info/WHEEL
robot_description_builder-0.0.3.dist-info/license_files/LICENSE
robot_description_builder/exceptions.py
robot_description_builder/material.pyi
robot_description_builder/cluster_objects.py
robot_description_builder/__init__.pyi
robot_description_builder/material.py
robot_description_builder/__init__.py
robot_description_builder/joint.pyi
robot_description_builder/exceptions.pyi
robot_description_builder/transmission.py
robot_description_builder/cluster_objects.pyi
robot_description_builder/joint.py
robot_description_builder/transmission.pyi
robot_description_builder/py.typed
robot_description_builder/link/visual.pyi
robot_description_builder/link/geometry.py
robot_description_builder/link/visual.py
robot_description_builder/link/collision.py
robot_description_builder/link/__init__.pyi
robot_description_builder/link/__init__.py
robot_description_builder/link/collision.pyi
robot_description_builder/link/geometry.pyi
robot_description_builder/_internal.cpython-311-arm-linux-gnueabihf.so
robot_description_builder-0.0.3.dist-info/RECORD
