Metadata-Version: 2.1
Name: robot-description-builder
Version: 0.0.3
Classifier: Development Status :: 3 - Alpha
Classifier: Programming Language :: Rust
Classifier: Programming Language :: Python :: Implementation :: CPython
Classifier: Programming Language :: Python :: Implementation :: PyPy
Classifier: Programming Language :: Python :: 3 :: Only
Classifier: Programming Language :: Python :: 3.8
Classifier: Programming Language :: Python :: 3.9
Classifier: Programming Language :: Python :: 3.10
Classifier: Programming Language :: Python :: 3.11
Classifier: Programming Language :: Python :: 3.12
Classifier: License :: OSI Approved :: MIT License
Classifier: Intended Audience :: Developers
Classifier: Intended Audience :: Science/Research
Classifier: Operating System :: MacOS
Classifier: Operating System :: Microsoft :: Windows
Classifier: Operating System :: POSIX
Classifier: Operating System :: Unix
Classifier: Topic :: Scientific/Engineering
Classifier: Topic :: Software Development
Classifier: Typing :: Typed
License-File: LICENSE
Summary: A libary to create (valid) Robot descriptions
Keywords: urdf,robotics
License: MIT
Requires-Python: >=3.8
Project-URL: Homepage, https://github.com/SuperJappie08/robot-description-builder
Project-URL: Repository, https://github.com/SuperJappie08/robot-description-builder/tree/master/robot-description-builder-py
Project-URL: Changelog, https://github.com/SuperJappie08/robot-description-builder/tree/master/robot-description-builder-py/CHANGELOG.md
